[
  {
    "data": {
      "ts": {
        "url": "https://kinglotdke.github.io/horse-imu-labeling/horse10/chunks/horse10_chunk0001.csv"
      }
    },
    "predictions": [
      {
        "model_version": "init",
        "result": [
          {
            "id": "r1",
            "type": "timeserieslabels",
            "from_name": "label",
            "to_name": "ts",
            "origin": "manual",
            "value": {
              "start": 0,
              "end": 16542,
              "instant": false,
              "timeserieslabels": [
                "nan"
              ]
            }
          },
          {
            "id": "r2",
            "type": "timeserieslabels",
            "from_name": "label",
            "to_name": "ts",
            "origin": "manual",
            "value": {
              "start": 16542,
              "end": 24572,
              "instant": false,
              "timeserieslabels": [
                "tt"
              ]
            }
          },
          {
            "id": "r3",
            "type": "timeserieslabels",
            "from_name": "label",
            "to_name": "ts",
            "origin": "manual",
            "value": {
              "start": 24572,
              "end": 25579,
              "instant": false,
              "timeserieslabels": [
                "fw"
              ]
            }
          },
          {
            "id": "r4",
            "type": "timeserieslabels",
            "from_name": "label",
            "to_name": "ts",
            "origin": "manual",
            "value": {
              "start": 25579,
              "end": 30000,
              "instant": false,
              "timeserieslabels": [
                "wl"
              ]
            }
          }
        ]
      }
    ]
  },
  {
    "data": {
      "ts": {
        "url": "https://kinglotdke.github.io/horse-imu-labeling/horse10/chunks/horse10_chunk0002.csv"
      }
    },
    "predictions": [
      {
        "model_version": "init",
        "result": [
          {
            "id": "r5",
            "type": "timeserieslabels",
            "from_name": "label",
            "to_name": "ts",
            "origin": "manual",
            "value": {
              "start": 30000,
              "end": 44448,
              "instant": false,
              "timeserieslabels": [
                "wl"
              ]
            }
          },
          {
            "id": "r6",
            "type": "timeserieslabels",
            "from_name": "label",
            "to_name": "ts",
            "origin": "manual",
            "value": {
              "start": 44448,
              "end": 56677,
              "instant": false,
              "timeserieslabels": [
                "wr"
              ]
            }
          },
          {
            "id": "r7",
            "type": "timeserieslabels",
            "from_name": "label",
            "to_name": "ts",
            "origin": "manual",
            "value": {
              "start": 56677,
              "end": 60000,
              "instant": false,
              "timeserieslabels": [
                "tr"
              ]
            }
          }
        ]
      }
    ]
  },
  {
    "data": {
      "ts": {
        "url": "https://kinglotdke.github.io/horse-imu-labeling/horse10/chunks/horse10_chunk0003.csv"
      }
    },
    "predictions": [
      {
        "model_version": "init",
        "result": [
          {
            "id": "r8",
            "type": "timeserieslabels",
            "from_name": "label",
            "to_name": "ts",
            "origin": "manual",
            "value": {
              "start": 60000,
              "end": 72384,
              "instant": false,
              "timeserieslabels": [
                "tr"
              ]
            }
          },
          {
            "id": "r9",
            "type": "timeserieslabels",
            "from_name": "label",
            "to_name": "ts",
            "origin": "manual",
            "value": {
              "start": 72384,
              "end": 87442,
              "instant": false,
              "timeserieslabels": [
                "tl"
              ]
            }
          },
          {
            "id": "r10",
            "type": "timeserieslabels",
            "from_name": "label",
            "to_name": "ts",
            "origin": "manual",
            "value": {
              "start": 87442,
              "end": 90000,
              "instant": false,
              "timeserieslabels": [
                "cr"
              ]
            }
          }
        ]
      }
    ]
  },
  {
    "data": {
      "ts": {
        "url": "https://kinglotdke.github.io/horse-imu-labeling/horse10/chunks/horse10_chunk0004.csv"
      }
    },
    "predictions": [
      {
        "model_version": "init",
        "result": [
          {
            "id": "r11",
            "type": "timeserieslabels",
            "from_name": "label",
            "to_name": "ts",
            "origin": "manual",
            "value": {
              "start": 90000,
              "end": 90487,
              "instant": false,
              "timeserieslabels": [
                "cr"
              ]
            }
          },
          {
            "id": "r12",
            "type": "timeserieslabels",
            "from_name": "label",
            "to_name": "ts",
            "origin": "manual",
            "value": {
              "start": 90487,
              "end": 91541,
              "instant": false,
              "timeserieslabels": [
                "tl"
              ]
            }
          },
          {
            "id": "r13",
            "type": "timeserieslabels",
            "from_name": "label",
            "to_name": "ts",
            "origin": "manual",
            "value": {
              "start": 91541,
              "end": 93663,
              "instant": false,
              "timeserieslabels": [
                "cr"
              ]
            }
          },
          {
            "id": "r14",
            "type": "timeserieslabels",
            "from_name": "label",
            "to_name": "ts",
            "origin": "manual",
            "value": {
              "start": 93663,
              "end": 93991,
              "instant": false,
              "timeserieslabels": [
                "tl"
              ]
            }
          },
          {
            "id": "r15",
            "type": "timeserieslabels",
            "from_name": "label",
            "to_name": "ts",
            "origin": "manual",
            "value": {
              "start": 93991,
              "end": 94787,
              "instant": false,
              "timeserieslabels": [
                "cr"
              ]
            }
          },
          {
            "id": "r16",
            "type": "timeserieslabels",
            "from_name": "label",
            "to_name": "ts",
            "origin": "manual",
            "value": {
              "start": 94787,
              "end": 94939,
              "instant": false,
              "timeserieslabels": [
                "tl"
              ]
            }
          },
          {
            "id": "r17",
            "type": "timeserieslabels",
            "from_name": "label",
            "to_name": "ts",
            "origin": "manual",
            "value": {
              "start": 94939,
              "end": 95753,
              "instant": false,
              "timeserieslabels": [
                "cr"
              ]
            }
          },
          {
            "id": "r18",
            "type": "timeserieslabels",
            "from_name": "label",
            "to_name": "ts",
            "origin": "manual",
            "value": {
              "start": 95753,
              "end": 95925,
              "instant": false,
              "timeserieslabels": [
                "tl"
              ]
            }
          },
          {
            "id": "r19",
            "type": "timeserieslabels",
            "from_name": "label",
            "to_name": "ts",
            "origin": "manual",
            "value": {
              "start": 95925,
              "end": 98167,
              "instant": false,
              "timeserieslabels": [
                "cr"
              ]
            }
          },
          {
            "id": "r20",
            "type": "timeserieslabels",
            "from_name": "label",
            "to_name": "ts",
            "origin": "manual",
            "value": {
              "start": 98167,
              "end": 98613,
              "instant": false,
              "timeserieslabels": [
                "tl"
              ]
            }
          },
          {
            "id": "r21",
            "type": "timeserieslabels",
            "from_name": "label",
            "to_name": "ts",
            "origin": "manual",
            "value": {
              "start": 98613,
              "end": 99520,
              "instant": false,
              "timeserieslabels": [
                "cr"
              ]
            }
          },
          {
            "id": "r22",
            "type": "timeserieslabels",
            "from_name": "label",
            "to_name": "ts",
            "origin": "manual",
            "value": {
              "start": 99520,
              "end": 103525,
              "instant": false,
              "timeserieslabels": [
                "tl"
              ]
            }
          },
          {
            "id": "r23",
            "type": "timeserieslabels",
            "from_name": "label",
            "to_name": "ts",
            "origin": "manual",
            "value": {
              "start": 103525,
              "end": 105924,
              "instant": false,
              "timeserieslabels": [
                "cr"
              ]
            }
          },
          {
            "id": "r24",
            "type": "timeserieslabels",
            "from_name": "label",
            "to_name": "ts",
            "origin": "manual",
            "value": {
              "start": 105924,
              "end": 106374,
              "instant": false,
              "timeserieslabels": [
                "tr"
              ]
            }
          },
          {
            "id": "r25",
            "type": "timeserieslabels",
            "from_name": "label",
            "to_name": "ts",
            "origin": "manual",
            "value": {
              "start": 106374,
              "end": 106552,
              "instant": false,
              "timeserieslabels": [
                "wr"
              ]
            }
          },
          {
            "id": "r26",
            "type": "timeserieslabels",
            "from_name": "label",
            "to_name": "ts",
            "origin": "manual",
            "value": {
              "start": 106552,
              "end": 106798,
              "instant": false,
              "timeserieslabels": [
                "h"
              ]
            }
          },
          {
            "id": "r27",
            "type": "timeserieslabels",
            "from_name": "label",
            "to_name": "ts",
            "origin": "manual",
            "value": {
              "start": 106798,
              "end": 107847,
              "instant": false,
              "timeserieslabels": [
                "wr"
              ]
            }
          },
          {
            "id": "r28",
            "type": "timeserieslabels",
            "from_name": "label",
            "to_name": "ts",
            "origin": "manual",
            "value": {
              "start": 107847,
              "end": 111425,
              "instant": false,
              "timeserieslabels": [
                "tl"
              ]
            }
          },
          {
            "id": "r29",
            "type": "timeserieslabels",
            "from_name": "label",
            "to_name": "ts",
            "origin": "manual",
            "value": {
              "start": 111425,
              "end": 119432,
              "instant": false,
              "timeserieslabels": [
                "cl"
              ]
            }
          },
          {
            "id": "r30",
            "type": "timeserieslabels",
            "from_name": "label",
            "to_name": "ts",
            "origin": "manual",
            "value": {
              "start": 119432,
              "end": 120000,
              "instant": false,
              "timeserieslabels": [
                "tl"
              ]
            }
          }
        ]
      }
    ]
  },
  {
    "data": {
      "ts": {
        "url": "https://kinglotdke.github.io/horse-imu-labeling/horse10/chunks/horse10_chunk0005.csv"
      }
    },
    "predictions": [
      {
        "model_version": "init",
        "result": [
          {
            "id": "r31",
            "type": "timeserieslabels",
            "from_name": "label",
            "to_name": "ts",
            "origin": "manual",
            "value": {
              "start": 120000,
              "end": 120373,
              "instant": false,
              "timeserieslabels": [
                "tl"
              ]
            }
          },
          {
            "id": "r32",
            "type": "timeserieslabels",
            "from_name": "label",
            "to_name": "ts",
            "origin": "manual",
            "value": {
              "start": 120373,
              "end": 150000,
              "instant": false,
              "timeserieslabels": [
                "wl"
              ]
            }
          }
        ]
      }
    ]
  },
  {
    "data": {
      "ts": {
        "url": "https://kinglotdke.github.io/horse-imu-labeling/horse10/chunks/horse10_chunk0006.csv"
      }
    },
    "predictions": [
      {
        "model_version": "init",
        "result": [
          {
            "id": "r33",
            "type": "timeserieslabels",
            "from_name": "label",
            "to_name": "ts",
            "origin": "manual",
            "value": {
              "start": 150000,
              "end": 169145,
              "instant": false,
              "timeserieslabels": [
                "wl"
              ]
            }
          },
          {
            "id": "r34",
            "type": "timeserieslabels",
            "from_name": "label",
            "to_name": "ts",
            "origin": "manual",
            "value": {
              "start": 169145,
              "end": 169885,
              "instant": false,
              "timeserieslabels": [
                "h"
              ]
            }
          },
          {
            "id": "r35",
            "type": "timeserieslabels",
            "from_name": "label",
            "to_name": "ts",
            "origin": "manual",
            "value": {
              "start": 169885,
              "end": 180000,
              "instant": false,
              "timeserieslabels": [
                "endtest"
              ]
            }
          }
        ]
      }
    ]
  },
  {
    "data": {
      "ts": {
        "url": "https://kinglotdke.github.io/horse-imu-labeling/horse10/chunks/horse10_chunk0007.csv"
      }
    },
    "predictions": [
      {
        "model_version": "init",
        "result": [
          {
            "id": "r36",
            "type": "timeserieslabels",
            "from_name": "label",
            "to_name": "ts",
            "origin": "manual",
            "value": {
              "start": 180000,
              "end": 182090,
              "instant": false,
              "timeserieslabels": [
                "endtest"
              ]
            }
          },
          {
            "id": "r37",
            "type": "timeserieslabels",
            "from_name": "label",
            "to_name": "ts",
            "origin": "manual",
            "value": {
              "start": 182090,
              "end": 189677,
              "instant": false,
              "timeserieslabels": [
                "nan"
              ]
            }
          }
        ]
      }
    ]
  }
]